git_sherlock/__init__.py
git_sherlock/beautifying.py
git_sherlock/conversation.py
git_sherlock/gemini.py
git_sherlock/main.py
git_sherlock/terminal.py
git_sherlock/utils.py
git_sherlock_tool-1.2.dist-info/METADATA
git_sherlock_tool-1.2.dist-info/WHEEL
git_sherlock_tool-1.2.dist-info/entry_points.txt
git_sherlock_tool-1.2.dist-info/top_level.txt
git_sherlock_tool-1.2.dist-info/RECORD
