Metadata-Version: 2.1
Name: git-sherlock-tool
Version: 1.2
Requires-Dist: ftfy ==6.2.3
Requires-Dist: pandas ==2.2.2
Requires-Dist: protobuf
Requires-Dist: PyGithub ==2.4.0
Requires-Dist: python-dotenv ==1.0.1
Requires-Dist: Requests ==2.32.3
Requires-Dist: rich ==13.8.0
Requires-Dist: google.generativeai
